{
    "SPM_diffusers": {
        "fid": 126.30930029876544,
        "clip": 22.125659258860463
    },
    "Scissorhands_diffusers": {
        "fid": 148.845444432828,
        "clip": 22.064091340550835
    },
    "Salun_diffusers": {
        "fid": 124.29839213098302,
        "clip": 22.122203862892007
    },
    "EraseDiff_diffusers": {
        "fid": 126.48577125848612,
        "clip": 22.164131236526202
    },
    "ESD_diffusers": {
        "fid": 127.22129251752477,
        "clip": 22.094512327662056
    },
    "UCE_diffusers": {
        "fid": 126.74573779319206,
        "clip": 22.184111181295144
    },
    "MACE_diffusers": {
        "fid": 122.73313872300992,
        "clip": 22.21606398528477
    },
    "FMN_diffusers": {
        "fid": 127.43222026883944,
        "clip": 22.09109806564619
    },
    "RECE_diffusers": {
        "fid": 124.46240672746956,
        "clip": 22.144146757305794
    },
    "STEREO_diffusers": {
        "fid": 130.0273239389872,
        "clip": 22.110780895880932
    },
    "AdvUnlearn_diffusers": {
        "fid": 129.377566564443,
        "clip": 22.113598769565797
    }
}